claude_context/__init__.py
claude_context/chains.py
claude_context/classifier.py
claude_context/cli.py
claude_context/git_integration.py
claude_context/index.py
claude_context/migration.py
claude_context/project.py
claude_context/storage.py
claude_context/schema/v2.sql
claude_context-0.2.1.dist-info/METADATA
claude_context-0.2.1.dist-info/WHEEL
claude_context-0.2.1.dist-info/entry_points.txt
claude_context-0.2.1.dist-info/RECORD
