Metadata-Version: 2.4
Name: claude-context
Version: 0.2.1
Summary: Manage project-wide and branch-specific context documents for Claude sessions
Author-email: akatz-ai <katzfeyalex+akatzgh@gmail.com>
License: MIT
Keywords: claude,claude-code,cli,exploration,github,workspace
Classifier: Development Status :: 3 - Alpha
Classifier: Intended Audience :: Developers
Classifier: License :: OSI Approved :: MIT License
Classifier: Programming Language :: Python :: 3
Classifier: Programming Language :: Python :: 3.10
Classifier: Programming Language :: Python :: 3.11
Classifier: Programming Language :: Python :: 3.12
Requires-Python: >=3.9
